rfdetr_doclayout/__init__.py
rfdetr_doclayout/py.typed
rfdetr_doclayout/rfdetr.py
rfdetr_doclayout/utils.py
rfdetr_doclayout-0.1.0.dist-info/WHEEL
rfdetr_doclayout-0.1.0.dist-info/METADATA
rfdetr_doclayout-0.1.0.dist-info/RECORD
