Metadata-Version: 2.3
Name: rfdetr-doclayout
Version: 0.1.0
Summary: Add your description here
Author: neka-nat
Author-email: neka-nat <nekanat.stock@gmail.com>
Requires-Dist: numpy>=1.26.4
Requires-Dist: onnxruntime>=1.23.2
Requires-Dist: tqdm>=4.67.1
Requires-Dist: onnx>=1.19.0 ; extra == 'export'
Requires-Dist: onnxscript>=0.5.0 ; extra == 'export'
Requires-Dist: onnxsim>=0.4.36 ; extra == 'export'
Requires-Dist: boto3>=1.40.60 ; extra == 'train'
Requires-Dist: python-dotenv>=1.2.0 ; extra == 'train'
Requires-Dist: rfdetr[metrics]>=1.3.0 ; extra == 'train'
Requires-Dist: sagemaker>=2.253.1 ; extra == 'train'
Requires-Python: >=3.12
Provides-Extra: export
Provides-Extra: train
